tubefeed/__init__.py
tubefeed/__main__.py
tubefeed/database/BaseDB.py
tubefeed/database/__init__.py
tubefeed/feed/Feed.py
tubefeed/feed/FeedChannel.py
tubefeed/feed/FeedChannelImage.py
tubefeed/feed/FeedChannelItem.py
tubefeed/feed/FeedChannelItemImage.py
tubefeed/feed/__init__.py
tubefeed/media/Chapter.py
tubefeed/media/ChapterList.py
tubefeed/media/Downloader.py
tubefeed/media/__init__.py
tubefeed/provider/Provider.py
tubefeed/provider/__init__.py
tubefeed/provider/twitch/Feed.py
tubefeed/provider/twitch/TwitchProvider.py
tubefeed/provider/twitch/__init__.py
tubefeed/provider/twitch/database/Channel.py
tubefeed/provider/twitch/database/Database.py
tubefeed/provider/twitch/database/File.py
tubefeed/provider/twitch/database/Video.py
tubefeed/provider/twitch/database/__init__.py
tubefeed/provider/twitch/twitch_api/TwChannel.py
tubefeed/provider/twitch/twitch_api/TwVideo.py
tubefeed/provider/twitch/twitch_api/Twitch.py
tubefeed/provider/twitch/twitch_api/__init__.py
tubefeed/provider/youtube/ChapterList.py
tubefeed/provider/youtube/Feed.py
tubefeed/provider/youtube/YouTubeProvider.py
tubefeed/provider/youtube/__init__.py
tubefeed/provider/youtube/database/Channel.py
tubefeed/provider/youtube/database/Database.py
tubefeed/provider/youtube/database/File.py
tubefeed/provider/youtube/database/Playlist.py
tubefeed/provider/youtube/database/PlaylistUnion.py
tubefeed/provider/youtube/database/Thumbnail.py
tubefeed/provider/youtube/database/Video.py
tubefeed/provider/youtube/database/__init__.py
tubefeed/provider/youtube/sb_api/SBSegment.py
tubefeed/provider/youtube/sb_api/SponsorBlock.py
tubefeed/provider/youtube/sb_api/__init__.py
tubefeed/provider/youtube/yt_api/YTChannel.py
tubefeed/provider/youtube/yt_api/YTError.py
tubefeed/provider/youtube/yt_api/YTPlaylist.py
tubefeed/provider/youtube/yt_api/YTPlaylistItem.py
tubefeed/provider/youtube/yt_api/YTThumbnail.py
tubefeed/provider/youtube/yt_api/YTVideo.py
tubefeed/provider/youtube/yt_api/YouTube.py
tubefeed-3.0.9.dist-info/licenses/LICENSE
tubefeed-3.0.9.dist-info/METADATA
tubefeed-3.0.9.dist-info/WHEEL
tubefeed-3.0.9.dist-info/top_level.txt
tubefeed-3.0.9.dist-info/RECORD
