Metadata-Version: 2.4
Name: tubefeed
Version: 3.0.9
Summary: seamlessly integrate YouTube with Audiobookshelf
Home-page: https://gitlab.com/troebs/tubefeed
Author: Eric Tröbs
Author-email: eric.troebs@tu-ilmenau.de
Project-URL: Bug Tracker, https://gitlab.com/troebs/tubefeed/-/issues
Classifier: Programming Language :: Python :: 3
Classifier: License :: OSI Approved :: MIT License
Classifier: Operating System :: OS Independent
Requires-Python: >=3.10
License-File: LICENSE
Requires-Dist: aiohttp~=3.12
Requires-Dist: aiosqlite~=0.21
Requires-Dist: yt-dlp[default]==2026.1.29
Dynamic: author
Dynamic: author-email
Dynamic: classifier
Dynamic: description
Dynamic: description-content-type
Dynamic: home-page
Dynamic: license-file
Dynamic: project-url
Dynamic: requires-dist
Dynamic: requires-python
Dynamic: summary
